warconvert/__init__.py
warconvert/__main__.py
warconvert-0.0.5.dist-info/LICENSE
warconvert-0.0.5.dist-info/METADATA
warconvert-0.0.5.dist-info/WHEEL
warconvert-0.0.5.dist-info/top_level.txt
warconvert-0.0.5.dist-info/RECORD
